LICENSE
MANIFEST.in
README.rst
setup.py
krankshaft/__init__.py
krankshaft/__init__.pyc
krankshaft/api.py
krankshaft/api.pyc
krankshaft/auth.py
krankshaft/auth.pyc
krankshaft/authn.py
krankshaft/authn.pyc
krankshaft/authz.py
krankshaft/authz.pyc
krankshaft/exceptions.py
krankshaft/exceptions.pyc
krankshaft/models.py
krankshaft/models.pyc
krankshaft/query.py
krankshaft/resource.py
krankshaft/serializable.pyc
krankshaft/serializer.py
krankshaft/serializer.pyc
krankshaft/throttle.py
krankshaft/throttle.pyc
krankshaft/util.py
krankshaft/util.pyc
krankshaft/valid.py
krankshaft.egg-info/PKG-INFO
krankshaft.egg-info/SOURCES.txt
krankshaft.egg-info/dependency_links.txt
krankshaft.egg-info/not-zip-safe
krankshaft.egg-info/requires.txt
krankshaft.egg-info/top_level.txt
krankshaft/compat/__init__.py
krankshaft/compat/xact.py
krankshaft/static/js/backbone-krankshaft.js
krankshaft/static/js/krankshaft.js
tests/__init__.py
tests/base.py
tests/settings.py
tests/urls.py
tests/wsgi.py
tests/krankshaft/__init__.py
tests/krankshaft/test_api.py
tests/krankshaft/test_query.py
tests/krankshaft/test_resource.py
tests/krankshaft/test_serializer.py
tests/krankshaft/test_throttle.py
tests/krankshaft/test_valid.py