Metadata-Version: 1.1
Name: krankshaft
Version: 0.3.7
Summary: A Web API Framework (with Django, ...)
Home-page: https://github.com/dlamotte/krankshaft
Author: Dan LaMotte
Author-email: lamotte85@gmail.com
License: MIT
Platform: UNKNOWN
Classifier: Development Status :: 3 - Alpha
Classifier: Environment :: Web Environment
Classifier: Intended Audience :: Developers
Classifier: License :: OSI Approved :: MIT License
Classifier: Operating System :: OS Independent
Classifier: Programming Language :: Python
Classifier: Topic :: Utilities
